tkintertools/__init__.py
tkintertools/__main__.py
tkintertools/constants.py
tkintertools_test-3.dist-info/LICENSE
tkintertools_test-3.dist-info/METADATA
tkintertools_test-3.dist-info/WHEEL
tkintertools_test-3.dist-info/top_level.txt
tkintertools_test-3.dist-info/RECORD
