Metadata-Version: 2.1
Name: tkintertools-test
Version: 3
Summary: An auxiliary module of the tkinder module
Home-page: https://gitcode.net/weixin_62651706/tkintertools
Author: Xiaokang2022
Author-email: 2951256653@qq.com
Classifier: Programming Language :: Python :: 3
Classifier: License :: OSI Approved :: Mulan Permissive Software License v2 (MulanPSL-2.0)
Classifier: Operating System :: OS Independent
License-File: LICENSE
